MANIFEST.in
README.md
setup.cfg
setup.py
kae/__init__.py
kae/action.py
kae/app.py
kae/cli.py
kae/commands.py
kae/create_app.py
kae/docker.py
kae/job.py
kae/spark.py
kae/test.py
kae/utils.py
kae.egg-info/PKG-INFO
kae.egg-info/SOURCES.txt
kae.egg-info/dependency_links.txt
kae.egg-info/entry_points.txt
kae.egg-info/requires.txt
kae.egg-info/top_level.txt
kae/tpl/Readme.md
kae/tpl/app.yaml
kae/tpl/gitlab-ci.yml
kae/tpl/django/readme.md
kae/tpl/flask/Dockerfile
kae/tpl/flask/app.py
kae/tpl/flask/gunicorn_config.py
kae/tpl/flask/requirements.txt
kae/tpl/go/Dockerfile
kae/tpl/go/main.go
kae/tpl/node/Dockerfile
kae/tpl/node/readme.md
kae/tpl/tornado/Dockerfile
kae/tpl/tornado/app.py
kae/tpl/tornado/requirements.txt