Metadata-Version: 2.1
Name: kae
Version: 0.0.15
Summary: kubernetes app engine command line tool
Home-page: https://github.com/kaecloud/cli
Author: Yu Yang
Author-email: yangyu@geetest.com
License: UNKNOWN
Platform: UNKNOWN
